screeny/__init__.py
screeny/image.py
screeny/mouse.py
screeny/screeny.py
screeny-0.5.0.dist-info/LICENSE
screeny-0.5.0.dist-info/LICENSE-3RD-Party.txt
screeny-0.5.0.dist-info/METADATA
screeny-0.5.0.dist-info/WHEEL
screeny-0.5.0.dist-info/top_level.txt
screeny-0.5.0.dist-info/RECORD
