Metadata-Version: 2.1
Name: screeny
Version: 0.5.0
Summary: A simple python library for working with screens and images.
Author: Paul Pol
Author-email: mail@paul-pol.de
License: MIT
Classifier: License :: OSI Approved :: MIT License
Classifier: Programming Language :: Python :: 3
License-File: LICENSE
License-File: LICENSE-3RD-Party.txt
Requires-Dist: numpy
Requires-Dist: opencv-python
Requires-Dist: mss
Requires-Dist: PySide6
Requires-Dist: matplotlib
Requires-Dist: pytesseract
